azure_kinect_apiserver/__init__.py
azure_kinect_apiserver/__main__.py
azure_kinect_apiserver/apiserver/__init__.py
azure_kinect_apiserver/apiserver/app.py
azure_kinect_apiserver/apiserver/server.py
azure_kinect_apiserver/client/__init__.py
azure_kinect_apiserver/client/restful/__init__.py
azure_kinect_apiserver/client/restful/client.py
azure_kinect_apiserver/client/restful/errors.py
azure_kinect_apiserver/client/restful/types.py
azure_kinect_apiserver/client/restful/api/__init__.py
azure_kinect_apiserver/client/restful/api/default/__init__.py
azure_kinect_apiserver/client/restful/api/default/get_status_v1_azure_status_get.py
azure_kinect_apiserver/client/restful/api/default/root_get.py
azure_kinect_apiserver/client/restful/api/default/single_shot_v1_azure_single_shot_get.py
azure_kinect_apiserver/client/restful/api/default/start_recording_v1_azure_start_post.py
azure_kinect_apiserver/client/restful/api/default/stop_recording_v1_azure_stop_post.py
azure_kinect_apiserver/client/restful/api/default/stop_single_shot_v1_azure_single_shot_delete.py
azure_kinect_apiserver/client/restful/models/__init__.py
azure_kinect_apiserver/client/restful/models/http_validation_error.py
azure_kinect_apiserver/client/restful/models/validation_error.py
azure_kinect_apiserver/cmd/__init__.py
azure_kinect_apiserver/cmd/analyze.py
azure_kinect_apiserver/cmd/calibration.py
azure_kinect_apiserver/cmd/configure.py
azure_kinect_apiserver/cmd/decode.py
azure_kinect_apiserver/cmd/multical.py
azure_kinect_apiserver/common/Config.py
azure_kinect_apiserver/common/DataModel.py
azure_kinect_apiserver/common/MulticalCamera.py
azure_kinect_apiserver/common/__init__.py
azure_kinect_apiserver/common/functional.py
azure_kinect_apiserver/common/point.py
azure_kinect_apiserver/decoder/StateMachine.py
azure_kinect_apiserver/decoder/__init__.py
azure_kinect_apiserver/decoder/aruco.py
azure_kinect_apiserver/decoder/wrapper.py
azure_kinect_apiserver/thirdparty/__init__.py
azure_kinect_apiserver-0.2.3.dist-info/METADATA
azure_kinect_apiserver-0.2.3.dist-info/WHEEL
azure_kinect_apiserver-0.2.3.dist-info/top_level.txt
azure_kinect_apiserver-0.2.3.dist-info/RECORD
