Metadata-Version: 2.1
Name: azure-kinect-apiserver
Version: 0.2.3
Summary: Azure Kinect APIServer
Author: davidliyutong
Author-email: davidliyutong@sjtu.edu.cn
Requires-Python: >=3.7
Requires-Dist: pyyaml
Requires-Dist: opencv-python (~=4.7.0)
Requires-Dist: numpy
Requires-Dist: tqdm
Requires-Dist: fastapi (>=0.87.0)
Requires-Dist: uvicorn (>=0.20.0)
Requires-Dist: py-cli-interaction
Requires-Dist: httpx
Requires-Dist: open3d
Requires-Dist: requests
Requires-Dist: pandas
Requires-Dist: plyer
